src/__init__.py
src/md.py
src/parser.py
src/tdoc.py
tdoc-0.2.dist-info/DESCRIPTION.rst
tdoc-0.2.dist-info/METADATA
tdoc-0.2.dist-info/RECORD
tdoc-0.2.dist-info/WHEEL
tdoc-0.2.dist-info/entry_points.txt
tdoc-0.2.dist-info/metadata.json
tdoc-0.2.dist-info/top_level.txt
