Metadata-Version: 2.0
Name: tdoc
Version: 0.2
Summary: Python To Markdown Documentation Tool
Home-page: https://github.com/Ryanb58/tdoc
Author: Taylor Brazelton
Author-email: ryanb58@live.com
License: UNKNOWN
Keywords: doc,gen,api,ast,auto
Platform: UNKNOWN
Requires-Dist: Click
Requires-Dist: mkdocs
